cardscan_client/__init__.py
cardscan_client/api/__init__.py
cardscan_client/api/card_scan_api.py
cardscan_client/api_client.py
cardscan_client/api_response.py
cardscan_client/configuration.py
cardscan_client/docs/Address.md
cardscan_client/docs/AddressType.md
cardscan_client/docs/ApiErrorResponse.md
cardscan_client/docs/CHCPayerRecord.md
cardscan_client/docs/CardApiResponse.md
cardscan_client/docs/CardApiResponseDetails.md
cardscan_client/docs/CardApiResponseEnrichedResults.md
cardscan_client/docs/CardApiResponseImages.md
cardscan_client/docs/CardApiResponseImagesBack.md
cardscan_client/docs/CardApiResponseImagesFront.md
cardscan_client/docs/CardPerformance200Response.md
cardscan_client/docs/CardResponseMetadata.md
cardscan_client/docs/CardScanApi.md
cardscan_client/docs/CardState.md
cardscan_client/docs/CardWebsocketEvent.md
cardscan_client/docs/CoInsurance.md
cardscan_client/docs/CoPayment.md
cardscan_client/docs/CopayCategory.md
cardscan_client/docs/CopayDeductibleService.md
cardscan_client/docs/CoverageSummary.md
cardscan_client/docs/CreateCardRequest.md
cardscan_client/docs/CreateCardRequestBackside.md
cardscan_client/docs/CreateEligibilityRequest.md
cardscan_client/docs/CustomPayerRecord.md
cardscan_client/docs/Deductible.md
cardscan_client/docs/DirectUpload200Response.md
cardscan_client/docs/DirectUpload200ResponseMetadata.md
cardscan_client/docs/DirectUploadRequest.md
cardscan_client/docs/EligibilityApiResponse.md
cardscan_client/docs/EligibilityApiResponseEligibilityRequest.md
cardscan_client/docs/EligibilityApiResponseEligibilityRequestProvider.md
cardscan_client/docs/EligibilityApiResponseEligibilityRequestSubscriber.md
cardscan_client/docs/EligibilityError.md
cardscan_client/docs/EligibilityInfo.md
cardscan_client/docs/EligibilityState.md
cardscan_client/docs/EligibilitySummarizedResponse.md
cardscan_client/docs/EligibilityWebsocketEvent.md
cardscan_client/docs/EnrichedAddressResultInner.md
cardscan_client/docs/EnrichedCopayResultInner.md
cardscan_client-0.12.0.dist-info/METADATA
cardscan_client-0.12.0.dist-info/WHEEL
cardscan_client-0.12.0.dist-info/RECORD
