Metadata-Version: 2.4
Name: cardscan-client
Version: 0.12.0
Summary: Python CardScan API client
License: SEE LICENSE IN LICENSE.md
Keywords: CardScan,CardScan client,CardScan API client
Author: Team CardScan
Author-email: dev@cardscan.ai
Requires-Python: >=3.8,<4.0
Classifier: License :: Other/Proprietary License
Classifier: Programming Language :: Python :: 3
Classifier: Programming Language :: Python :: 3.8
Classifier: Programming Language :: Python :: 3.9
Classifier: Programming Language :: Python :: 3.10
Classifier: Programming Language :: Python :: 3.11
Classifier: Programming Language :: Python :: 3.12
Classifier: Programming Language :: Python :: 3.13
Classifier: Programming Language :: Python :: 3.14
Requires-Dist: aenum (>=3.1.11)
Requires-Dist: aiohttp (>=3.8.4)
Requires-Dist: pydantic (>=2.0,<3.0)
Requires-Dist: python-dateutil (>=2.8.2)
Requires-Dist: urllib3 (>=1.25.3)
Requires-Dist: websocket-client (>=1.8.0)
Requires-Dist: websockets (>=12.0)
Project-URL: Repository, https://github.com/CardScan-ai/api-clients.git
